json_serialize.py
JSON_Serialize-1.0.2.dist-info/LICENSE
JSON_Serialize-1.0.2.dist-info/METADATA
JSON_Serialize-1.0.2.dist-info/WHEEL
JSON_Serialize-1.0.2.dist-info/top_level.txt
JSON_Serialize-1.0.2.dist-info/RECORD
