Metadata-Version: 2.1
Name: JSON-Serialize
Version: 1.0.2
Summary: Module that serializes Python objects into JSON
Home-page: https://github.com/gaming32/json-serialize
Author: Gaming32
Author-email: gaming32i64@gmail.com
License: License :: OSI Approved :: GNU General Public License v3 (GPLv3)
Platform: UNKNOWN
